examples/__init__.py
examples/basic/__init__.py
examples/basic/main.py
examples/basic/podfactory.py
galileofaas/__init__.py
galileofaas/constants.py
galileofaas/connections/__init__.py
galileofaas/context/__init__.py
galileofaas/context/daemon.py
galileofaas/context/model.py
galileofaas/context/platform/__init__.py
galileofaas/context/platform/deployment/__init__.py
galileofaas/context/platform/deployment/factory.py
galileofaas/context/platform/deployment/k8s.py
galileofaas/context/platform/network/__init__.py
galileofaas/context/platform/network/factory.py
galileofaas/context/platform/node/__init__.py
galileofaas/context/platform/node/factory.py
galileofaas/context/platform/node/model.py
galileofaas/context/platform/pod/__init__.py
galileofaas/context/platform/pod/factory.py
galileofaas/context/platform/replica/__init__.py
galileofaas/context/platform/replica/factory.py
galileofaas/context/platform/replica/k8s.py
galileofaas/context/platform/replica/model.py
galileofaas/context/platform/telemetry/__init__.py
galileofaas/context/platform/telemetry/factory.py
galileofaas/context/platform/telemetry/rds.py
galileofaas/context/platform/telemetry/static.py
galileofaas/context/platform/telemetry/util.py
galileofaas/context/platform/trace/__init__.py
galileofaas/context/platform/trace/factory.py
galileofaas/context/platform/trace/rds.py
galileofaas/context/platform/zone/__init__.py
galileofaas/context/platform/zone/factory.py
galileofaas/system/__init__.py
galileofaas/system/core.py
galileofaas/system/faas.py
galileofaas/system/metrics.py
galileofaas/system/k8s/__init__.py
galileofaas/system/k8s/create.py
galileofaas/system/k8s/delete.py
galileofaas/util/__init__.py
galileofaas/util/cpu.py
galileofaas/util/network.py
galileofaas/util/pubsub.py
galileofaas/util/storage.py
galileofaas/util/telemetry.py
edgerun_galileo_faas-0.0.1.dev9.dist-info/LICENSE
edgerun_galileo_faas-0.0.1.dev9.dist-info/METADATA
edgerun_galileo_faas-0.0.1.dev9.dist-info/WHEEL
edgerun_galileo_faas-0.0.1.dev9.dist-info/top_level.txt
edgerun_galileo_faas-0.0.1.dev9.dist-info/RECORD
