Metadata-Version: 2.1
Name: edgerun-galileo-faas
Version: 0.0.1.dev9
Summary: Galileo FaaS
Home-page: https://github.com/edgerun/galileo-faas
Author: Philipp Raith, Thomas Rausch
Author-email: p.raith@dsg.tuwien.ac.at, t.rausch@dsg.tuwien.ac.at
License: UNKNOWN
Platform: UNKNOWN
Classifier: Programming Language :: Python :: 3
Classifier: Operating System :: OS Independent
License-File: LICENSE
Requires-Dist: etcd3 (==0.12.0)
Requires-Dist: influxdb-client (>=1.30.0)
Requires-Dist: kubernetes (>=18.20.0)
Requires-Dist: redis (==3.5.3)
Requires-Dist: telemc (>=0.3.0)
Requires-Dist: galileo-db (>=0.10.5.dev2)
Requires-Dist: dataclasses-json (==0.5.7)
Requires-Dist: pandas (>=1.2.5)
Requires-Dist: edgerun-skippy-core
Requires-Dist: protobuf (==3.20.1)
